presalytics_story/__init__.py
presalytics_story/api_client.py
presalytics_story/configuration.py
presalytics_story/exceptions.py
presalytics_story/rest.py
presalytics_story/api/__init__.py
presalytics_story/api/default_api.py
presalytics_story/models/__init__.py
presalytics_story/models/base_model.py
presalytics_story/models/ooxml_document.py
presalytics_story/models/ooxml_document_all_of.py
presalytics_story/models/outline.py
presalytics_story/models/permission_type.py
presalytics_story/models/permission_type_all_of.py
presalytics_story/models/problem_detail.py
presalytics_story/models/story.py
presalytics_story/models/story_all_of.py
presalytics_story/models/story_collaborator.py
presalytics_story/models/story_collaborator_all_of.py
presalytics_story/models/story_outline_history.py
presalytics_story/models/story_outline_history_all_of.py
presalytics_story-0.1.20.dist-info/LICENSE
presalytics_story-0.1.20.dist-info/METADATA
presalytics_story-0.1.20.dist-info/WHEEL
presalytics_story-0.1.20.dist-info/top_level.txt
presalytics_story-0.1.20.dist-info/RECORD
