Metadata-Version: 2.1
Name: presalytics-story
Version: 0.1.20
Summary: Story API
Home-page: http://github.com/presalytics/story-python-client
Author-email: kevin@presalytics.io
License: UNKNOWN
Keywords: Presaltyics,Story API
Platform: UNKNOWN
Requires-Dist: urllib3 (>=1.15)
Requires-Dist: six (>=1.10)
Requires-Dist: certifi
Requires-Dist: python-dateutil
